LICENSE
MANIFEST.in
README.rst
setup.py
gapic_google_cloud_datastore_v1.egg-info/PKG-INFO
gapic_google_cloud_datastore_v1.egg-info/SOURCES.txt
gapic_google_cloud_datastore_v1.egg-info/dependency_links.txt
gapic_google_cloud_datastore_v1.egg-info/namespace_packages.txt
gapic_google_cloud_datastore_v1.egg-info/requires.txt
gapic_google_cloud_datastore_v1.egg-info/top_level.txt
google/__init__.py
google/cloud/__init__.py
google/cloud/gapic/__init__.py
google/cloud/gapic/datastore/__init__.py
google/cloud/gapic/datastore/v1/__init__.py
google/cloud/gapic/datastore/v1/datastore_client.py
google/cloud/gapic/datastore/v1/datastore_client_config.json
google/cloud/gapic/datastore/v1/enums.py